All_Linkedlist_concat/All_Linkedlist_concat.py
All_Linkedlist_concat-0.0.3.dist-info/METADATA
All_Linkedlist_concat-0.0.3.dist-info/WHEEL
All_Linkedlist_concat-0.0.3.dist-info/top_level.txt
All_Linkedlist_concat-0.0.3.dist-info/RECORD
